sbo_selenium/__init__.py
sbo_selenium/conf.py
sbo_selenium/models.py
sbo_selenium/testcase.py
sbo_selenium/utils.py
sbo_selenium/management/__init__.py
sbo_selenium/management/commands/__init__.py
sbo_selenium/management/commands/selenium.py
sbo_selenium/static/js/axs_testing.js
sbo_selenium/tests/__init__.py
sbo_selenium/tests/test_accessibility.py
sbo_selenium/tests/test_arguments.py
sbo_selenium/tests/test_errors.py
sbo_selenium-0.7.2.dist-info/DESCRIPTION.rst
sbo_selenium-0.7.2.dist-info/METADATA
sbo_selenium-0.7.2.dist-info/metadata.json
sbo_selenium-0.7.2.dist-info/RECORD
sbo_selenium-0.7.2.dist-info/top_level.txt
sbo_selenium-0.7.2.dist-info/WHEEL
